_layout.cpython-37m-i386-linux-gnu.so
s_gd2/s_gd2.py
s_gd2/version.py
s_gd2/__init__.py
s_gd2/swig/layout.py
s_gd2/swig/__init__.py
sgdpy-1.4.1.dist-info/top_level.txt
sgdpy-1.4.1.dist-info/RECORD
sgdpy-1.4.1.dist-info/METADATA
sgdpy-1.4.1.dist-info/WHEEL
